nicenet/ActivationFunction.py
nicenet/Dataset.py
nicenet/Layer.py
nicenet/LossFunctions.py
nicenet/NeuralNetwork.py
nicenet/Types.py
nicenet/Utils.py
nicenet/__init__.py
nicenet-0.0.7.dist-info/LICENSE.txt
nicenet-0.0.7.dist-info/METADATA
nicenet-0.0.7.dist-info/WHEEL
nicenet-0.0.7.dist-info/top_level.txt
nicenet-0.0.7.dist-info/RECORD
