Metadata-Version: 2.1
Name: nicenet
Version: 0.0.7
Summary: Feed Forward Neural Networks
Home-page: https://github.com/Subhash3/Neural_Net_Using_NumPy/
Author: Subhash Sarangi
Author-email: subhashsarangi123@gmail.com
License: UNKNOWN
Platform: UNKNOWN
Classifier: Programming Language :: Python :: 3
Classifier: Programming Language :: Python :: 3.6
Classifier: Programming Language :: Python :: 3.7
Classifier: Operating System :: OS Independent
Requires-Python: >=3.6
Requires-Dist: cycler (==0.10.0)
Requires-Dist: kiwisolver (==1.3.1)
Requires-Dist: matplotlib (==3.3.4)
Requires-Dist: numpy (==1.19.5)
Requires-Dist: pillow (==8.2.0)
Requires-Dist: pyparsing (==3.0.0b2)
Requires-Dist: python-dateutil (==2.8.1)
Requires-Dist: six (==1.16.0)
Requires-Dist: tqdm (==4.61.0)
Requires-Dist: typing (==3.7.4.3)
